[
    "index.md",
    "author.html",
    "agenda.md",
    [
        "rest/index.md",
        "rest/fielding.md",
        "rest/definition.md",
        "rest/alt-definition.md",
        "rest/constraints.md",
        "rest/missing-constraint.md",
        "rest/uniform-iface.md"
    ],
    "misconceptions/index.md",
    [
        "misconceptions/identifiers.md",
        "misconceptions/restangular.md",
        "misconceptions/restangular2.md",
        "misconceptions/client-routing.md",
        "misconceptions/uri-conventions.md",
        "misconceptions/manipulation.md",
        "misconceptions/manipulation2.md",
        "misconceptions/self-descriptive.md",
        "misconceptions/client-side-bl.md",
        "misconceptions/hateoas.md",
        "misconceptions/documentation.md",
        "misconceptions/documentation2.md",
        "misconceptions/documentation3.md"
    ],
    [
        "hateoas-aiymi/index.md",
        "hateoas-aiymi/use-url.md",
        "hateoas-aiymi/use-url2.md",
        "hateoas-aiymi/use-headers.md",
        "hateoas-aiymi/empower-client.md",
        "hateoas-aiymi/server-drives-interaction.md",
        "hateoas-aiymi/server-drives-interaction2.md",
        "hateoas-aiymi/resource-based-routing.md",
        "hateoas-aiymi/resource-based-routing2.md"
    ],
    [
        "linked-data/index.md",
        {
            "filename": "linked-data/linked-data.md",
            "attr": {
                "data-background": "img/LOD_Cloud_2014.svg.png",
                "data-background-opaque": "true"
            }
        },
        "linked-data/json-ld.md",
        "linked-data/json-ld-expanded.md",
        {
            "filename": "linked-data/hydra.md",
            "attr": {
                "data-background": "img/hydra.jpg"
            }
        },
        {
            "filename": "linked-data/hydra2.md",
            "attr": {
                "data-background": "img/hydra.jpg"
            }
        },
        {
            "filename": "linked-data/hydra-inline.md",
            "attr": {
                "data-background": "img/hydra.jpg"
            }
        }
    ]
]
